{"data_mtime":1755241296,"dep_lines":[27,28,29,30,88,717,13,13,14,15,16,17,34,35,10,11,13,3,4,5,6,7,9,1,1,1,1],"dep_prios":[5,5,5,5,20,20,10,10,5,5,5,5,25,25,10,5,20,10,10,10,10,5,10,5,30,30,30],"dependencies":["torch._dynamo.variables.base","torch._dynamo.variables.constant","torch._dynamo.variables.functions","torch._dynamo.variables.iter","torch._dynamo.variables.tensor","torch._dynamo.variables.builtin","torch._dynamo.polyfills","torch._dynamo.variables","torch._dynamo.bytecode_transformation","torch._dynamo.exc","torch._dynamo.source","torch._dynamo.utils","torch._dynamo.codegen","torch._dynamo.symbolic_convert","torch.fx","torch._guards","torch._dynamo","collections","inspect","operator","types","typing","torch","builtins","_frozen_importlib","abc","torch.fx.proxy"],"hash":"c7147ebd9bea8718e598a46cbb7b0f644106139d","id":"torch._dynamo.variables.lists","ignore_all":true,"interface_hash":"04c7e1d481c62b5fb9155a37fabf24aaa84436c3","mtime":1741810120,"options":{"allow_redefinition":false,"allow_redefinition_new":false,"allow_untyped_globals":false,"always_false":[],"always_true":[],"bazel":false,"check_untyped_defs":true,"disable_bytearray_promotion":false,"disable_error_code":[],"disable_memoryview_promotion":false,"disabled_error_codes":[],"disallow_any_decorated":false,"disallow_any_explicit":false,"disallow_any_expr":false,"disallow_any_generics":false,"disallow_any_unimported":false,"disallow_incomplete_defs":true,"disallow_subclassing_any":false,"disallow_untyped_calls":false,"disallow_untyped_decorators":false,"disallow_untyped_defs":true,"enable_error_code":[],"enabled_error_codes":[],"extra_checks":false,"follow_imports":"normal","follow_imports_for_stubs":false,"follow_untyped_imports":false,"ignore_errors":false,"ignore_missing_imports":false,"implicit_optional":false,"implicit_reexport":true,"local_partial_types":false,"mypyc":false,"old_type_inference":false,"platform":"linux","plugins":[],"strict_bytes":false,"strict_concatenate":false,"strict_equality":true,"strict_optional":true,"warn_no_return":true,"warn_return_any":false,"warn_unreachable":false,"warn_unused_ignores":true},"path":"/home/ub/mambaforge/envs/dl/lib/python3.12/site-packages/torch/_dynamo/variables/lists.py","plugin_data":null,"size":38539,"suppressed":[],"version_id":"1.17.1"}